table_diff/__init__.py
table_diff/__main__.py
table_diff/cli.py
table_diff/df_helpers.py
table_diff/diff_evaluate.py
table_diff/diff_types.py
table_diff/log_helpers.py
table_diff/pdf_export.py
table_diff/report_common.py
table_diff/report_duckdb.py
table_diff/report_html.py
table_diff/report_markdown.py
table_diff/html_template/table_diff_report.html.jinja2
table_diff-0.2.3.dist-info/METADATA
table_diff-0.2.3.dist-info/WHEEL
table_diff-0.2.3.dist-info/entry_points.txt
table_diff-0.2.3.dist-info/licenses/LICENSE
table_diff-0.2.3.dist-info/RECORD
