Metadata-Version: 2.4
Name: table-diff
Version: 0.2.3
Summary: Tool to compare tables
Project-URL: Homepage, https://gitlab.com/parker-research/table-diff
Project-URL: Repository, https://gitlab.com/parker-research/table-diff
Project-URL: Issues, https://gitlab.com/parker-research/table-diff/-/issues
Author: parker-research
License-Expression: MIT
License-File: LICENSE
Classifier: License :: OSI Approved :: MIT License
Classifier: Operating System :: OS Independent
Classifier: Programming Language :: Python :: 3
Requires-Python: >=3.10
Requires-Dist: duckdb
Requires-Dist: jinja2>=3.1.6
Requires-Dist: loguru
Requires-Dist: minify-html>=0.18.1
Requires-Dist: ordered-set
Requires-Dist: polars==1.31.0
Requires-Dist: pyarrow
Requires-Dist: typed-argparse<1
